cmsc132/vhdl/ALU_1bit/mux_2to1.vhdl
LIBRARY ieee;
USE ieee.std_logic_1164.all;
---------------------------------
ENTITY mux_2to1 IS
   PORT (A, B, S: IN STD_LOGIC;
   C: OUT STD_LOGIC);
END mux_2to1;
--------------------------------

ARCHITECTURE pure_logic OF mux_2to1 IS
BEGIN
--- C <= (A AND NOT S) OR (B AND S);                       
   C <= A WHEN S='0' ELSE B;
END pure_logic;

cmsc132/vhdl/21mux/mux_2to1_tb.vhd
LIBRARY ieee;
USE ieee.std_logic_1164.all;

ENTITY mux_2to1_tb IS
END mux_2to1_tb;

architecture behavior of mux_2to1_tb is
   component mux_2to1 is 
      port (
         A, B, S: IN STD_LOGIC;
         C: OUT STD_LOGIC);
   end component;
   signal input: STD_LOGIC_VECTOR(2 downto 0);
   signal output: STD_LOGIC;

begin 
   uut: mux_2to1 port map (
      A => input(1),
      B => input(2),
      S => input(0),
      C => output
   );

   stim_proc: process
   begin
      input <= "000"; wait for 10 ns; assert output='0' report "000 failed,output= " & std_logic'image(output);
      input <= "001"; wait for 10 ns; assert output='0' report "001 failed,output= " & std_logic'image(output);
      input <= "010"; wait for 10 ns; assert output='1' report "010 failed,output= " & std_logic'image(output); 
      input <= "011"; wait for 10 ns; assert output='1' report "011 failed,output= " & std_logic'image(output);
      input <= "100"; wait for 10 ns; assert output='0' report "100 failed,output= " & std_logic'image(output);
      input <= "101"; wait for 10 ns; assert output='1' report "101 failed,output= " & std_logic'image(output); 
      input <= "110"; wait for 10 ns; assert output='0' report "110 failed,output= " & std_logic'image(output);
      input <= "111"; wait for 10 ns; assert output='1' report "111 failed,output= " & std_logic'image(output);
      wait;
   end process;
end;

cmsc132/vhdl/21mux/mux_2to1_tb.vcd
$date
  Wed Aug 19 21:21:54 2020
$end
$version
  GHDL v0
$end
$timescale
  1 fs
$end
$scope module standard $end
$upscope $end
$scope module std_logic_1164 $end
$upscope $end
$scope module mux_2to1_tb $end
$var reg 3 ! input[2:0] $end
$var reg 1 " output $end
$scope module uut $end
$var reg 1 # a $end
$var reg 1 $ b $end
$var reg 1 % s $end
$var reg 1 & c $end
$upscope $end
$upscope $end
$enddefinitions $end
#0
b000 !
0"
0#
0$
0%
0&
#10000000
b001 !
1%
#20000000
b010 !
1"
1#
0%
1&
#30000000
b011 !
0"
1%
0&
#40000000
b100 !
0#
1$
0%
#50000000
b101 !
1"
1%
1&
#60000000
b110 !
1#
0%
#70000000
b111 !
1%
