cmsc132/vhdl/fa/fa.vhd
library IEEE;
use IEEE.STD_LOGIC_1164.ALL;
 
entity full_adder_vhdl_code is
 Port ( A : in STD_LOGIC;
 B : in STD_LOGIC;
 Cin : in STD_LOGIC;
 S : out STD_LOGIC;
 Cout : out STD_LOGIC);
end full_adder_vhdl_code;
 
architecture gate_level of full_adder_vhdl_code is
 
begin
 
 S <= A XOR B XOR Cin ;
 Cout <= (A AND B) OR (Cin AND A) OR (Cin AND B) ;
 
end gate_level;

cmsc132/vhdl/fa/fa_tb.vhd
LIBRARY ieee;
USE ieee.std_logic_1164.ALL;
 
ENTITY Testbench_full_adder IS
END Testbench_full_adder;
 
ARCHITECTURE behavior OF Testbench_full_adder IS
 
 -- Component Declaration for the Unit Under Test (UUT)
 
 COMPONENT full_adder_vhdl_code
 PORT(
 A : IN std_logic;
 B : IN std_logic;
 Cin : IN std_logic;
 S : OUT std_logic;
 Cout : OUT std_logic
 );
 END COMPONENT;
 
 --Inputs
 signal A : std_logic := '0';
 signal B : std_logic := '0';
 signal Cin : std_logic := '0';
 
 --Outputs
 signal S : std_logic;
 signal Cout : std_logic;
 
BEGIN
 
 -- Instantiate the Unit Under Test (UUT)
 uut: full_adder_vhdl_code PORT MAP (
 A => A,
 B => B,
 Cin => Cin,
 S => S,
 Cout => Cout
 );
 
 -- Stimulus process
 stim_proc: process
 begin
 -- hold reset state for 100 ns.
 wait for 100 ns;
 
 -- insert stimulus here
 A <= '1';
 B <= '0';
 Cin <= '0';
 wait for 10 ns;
 
 A <= '0';
 B <= '1';
 Cin <= '0';
 wait for 10 ns;
 
 A <= '1';
 B <= '1';
 Cin <= '0';
 wait for 10 ns;
 
 A <= '0';
 B <= '0';
 Cin <= '1';
 wait for 10 ns;
 
 A <= '1';
 B <= '0';
 Cin <= '1';
 wait for 10 ns;
 
 A <= '0';
 B <= '1';
 Cin <= '1';
 wait for 10 ns;
 
 A <= '1';
 B <= '1';
 Cin <= '1';
 wait for 10 ns;
 
 end process;
 
END;

cmsc132/vhdl/fa/fa_tb.vcd
$date
  Thu Feb  6 15:32:08 2020
$end
$version
  GHDL v0
$end
$timescale
  1 fs
$end
$scope module standard $end
$upscope $end
$scope module std_logic_1164 $end
$upscope $end
$scope module testbench_full_adder $end
$var reg 1 ! a $end
$var reg 1 " b $end
$var reg 1 # cin $end
$var reg 1 $ s $end
$var reg 1 % cout $end
$scope module uut $end
$var reg 1 & a $end
$var reg 1 ' b $end
$var reg 1 ( cin $end
$var reg 1 ) s $end
$var reg 1 * cout $end
$upscope $end
$upscope $end
$enddefinitions $end
#0
0!
0"
0#
0$
0%
0&
0'
0(
0)
0*
#100000000
1!
1$
1&
1)
#110000000
0!
1"
0&
1'
#120000000
1!
0$
1%
1&
0)
1*
#130000000
0!
0"
1#
1$
0%
0&
0'
1(
1)
0*
#140000000
1!
0$
1%
1&
0)
1*
#150000000
0!
1"
0&
1'
#160000000
1!
1$
1&
1)
#170000000
#270000000
0"
0#
0%
0'
0(
0*
#280000000
0!
1"
0&
1'
#290000000
1!
0$
1%
1&
0)
1*
#300000000
0!
0"
1#
1$
0%
0&
0'
1(
1)
0*
#310000000
1!
0$
1%
1&
0)
1*
#320000000
0!
1"
0&
1'
#330000000
1!
1$
1&
1)
#340000000
#440000000
0"
0#
0%
0'
0(
0*
#450000000
0!
1"
0&
1'
#460000000
1!
0$
1%
1&
0)
1*
#470000000
0!
0"
1#
1$
0%
0&
0'
1(
1)
0*
#480000000
1!
0$
1%
1&
0)
1*
#490000000
0!
1"
0&
1'
#500000000
1!
1$
1&
1)
