cmsc132/vhdl/d_latch/d_latch.vhdl
LIBRARY ieee;
USE ieee.std_logic_1164.all;
---------------------------------
ENTITY d_latch IS
   PORT (C, D: IN STD_LOGIC;
   Q, Q_BAR: INOUT STD_LOGIC);
END d_latch;
--------------------------------
ARCHITECTURE pure_logic OF d_latch IS
BEGIN
   Q <= (C AND NOT D) NOR Q_BAR;
   Q_BAR <= (D AND C) NOR Q;
END pure_logic;

cmsc132/vhdl/dff/dff.vhdl
LIBRARY ieee;
USE ieee.std_logic_1164.ALL;
ENTITY dff is
   PORT( D: IN STD_LOGIC;
      C: IN STD_LOGIC;
      Q: INOUT STD_LOGIC;
      Q_BAR: INOUT STD_LOGIC);
END dff;
ARCHITECTURE behavioral OF dff IS
   COMPONENT d_latch IS
      PORT (C, D: IN STD_LOGIC;
      Q, Q_BAR: INOUT STD_LOGIC);
   END COMPONENT;
   SIGNAL u,v: STD_LOGIC;
   SIGNAL NOTC: STD_LOGIC := NOT C;
BEGIN
   u1: d_latch port map (D, C, u, v);
   u2: d_latch port map (u, NOTC, Q, Q_BAR);
END behavioral;

cmsc132/vhdl/dff/dff_tb.vhdl
LIBRARY ieee;
USE ieee.std_logic_1164.all;
ENTITY dff_tb IS
END dff_tb;
ARCHITECTURE behavior OF dff_tb IS
   --100Mhz
   CONSTANT frequency: integer := 100e6; 
   CONSTANT period : time := 1000 ms / frequency;
   SIGNAL clk : std_logic := '0';

   COMPONENT dff is
   PORT( D: IN STD_LOGIC;
      C: IN STD_LOGIC;
      Q: INOUT STD_LOGIC;
      Q_BAR: INOUT STD_LOGIC);
   END COMPONENT;

   SIGNAL D: STD_LOGIC := '0';
   SIGNAL Q: STD_LOGIC;
   SIGNAL Q_BAR: STD_LOGIC;
BEGIN 
   clk <= not clk after period;
   uut: dff PORT MAP (D, clk, Q, Q_BAR);
   stim_proc: PROCESS
   BEGIN
      D <= '0';
      WAIT FOR period / 2 ;

      D <= '1';
      WAIT FOR 20 ns;

      D <= '0';

      WAIT;
   END PROCESS;
END ARCHITECTURE;

cmsc132/vhdl/dff/dff_tb.vcd
$date
  Tue Aug 25 17:04:51 2020
$end
$version
  GHDL v0
$end
$timescale
  1 fs
$end
$scope module standard $end
$upscope $end
$scope module std_logic_1164 $end
$upscope $end
$scope module dff_tb $end
$var reg 1 ! clk $end
$var reg 1 " d $end
$var reg 1 # q $end
$var reg 1 $ q_bar $end
$scope module uut $end
$var reg 1 % d $end
$var reg 1 & c $end
$var reg 1 ' q $end
$var reg 1 ( q_bar $end
$var reg 1 ) u $end
$var reg 1 * v $end
$var reg 1 + notc $end
$scope module u1 $end
$var reg 1 , c $end
$var reg 1 - d $end
$var reg 1 . q $end
$var reg 1 / q_bar $end
$upscope $end
$scope module u2 $end
$var reg 1 0 c $end
$var reg 1 1 d $end
$var reg 1 2 q $end
$var reg 1 3 q_bar $end
$upscope $end
$upscope $end
$upscope $end
$enddefinitions $end
#0
0!
0"
U#
U$
0%
0&
U'
U(
U)
U*
1+
0,
0-
U.
U/
10
U1
U2
U3
#5000000
1"
1%
1-
#10000000
1!
1#
0$
1&
1'
0(
1)
0*
1,
1.
0/
11
12
03
#20000000
0!
0&
0,
#25000000
0"
0%
0-
#30000000
1!
0#
1$
1&
0'
1(
0)
1*
1,
0.
1/
01
02
13
#40000000
0!
0&
0,
#45000000
1"
1%
1-
#50000000
1!
1#
0$
1&
1'
0(
1)
0*
1,
1.
0/
11
12
03
#60000000
0!
0&
0,
#70000000
1!
1&
1,
#80000000
0!
0&
0,
#90000000
1!
1&
1,
#100000000
0!
0&
0,
#110000000
1!
1&
1,
#120000000
0!
0&
0,
#130000000
1!
1&
1,
#140000000
0!
0&
0,
#150000000
1!
1&
1,
#160000000
0!
0&
0,
#170000000
1!
1&
1,
#180000000
0!
0&
0,
#190000000
1!
1&
1,
#200000000
0!
0&
0,
#210000000
1!
1&
1,
#220000000
0!
0&
0,
#230000000
1!
1&
1,
#240000000
0!
0&
0,
#250000000
1!
1&
1,
#260000000
0!
0&
0,
#270000000
1!
1&
1,
#280000000
0!
0&
0,
#290000000
1!
1&
1,
#300000000
0!
0&
0,
#310000000
1!
1&
1,
#320000000
0!
0&
0,
#330000000
1!
1&
1,
#340000000
0!
0&
0,
#350000000
1!
1&
1,
#360000000
0!
0&
0,
#370000000
1!
1&
1,
#380000000
0!
0&
0,
#390000000
1!
1&
1,
#400000000
0!
0&
0,
#410000000
1!
1&
1,
#420000000
0!
0&
0,
#430000000
1!
1&
1,
#440000000
0!
0&
0,
#450000000
1!
1&
1,
#460000000
0!
0&
0,
#470000000
1!
1&
1,
#480000000
0!
0&
0,
#490000000
1!
1&
1,
#500000000
0!
0&
0,
