cmsc132/vhdl/trafficlite/trafficlite.vhdl
LIBRARY ieee;
USE ieee.std_logic_1164.all;
---------------------------------
ENTITY trafficlite IS
   PORT (
      EWCar, NSCar, clk: IN STD_LOGIC;
      EWLite, NSLite: OUT STD_LOGIC
   );
END trafficlite;
--------------------------------
ARCHITECTURE pure_logic OF trafficlite IS
   SIGNAL state : STD_LOGIC := '0'; 
BEGIN
   PROCESS
   BEGIN
      NSLite <= NOT state;
      EWLite <= state;
      IF (RISING_EDGE(clk)) THEN
         CASE state IS
            WHEN '0' =>
               state <= EWCar;
            WHEN '1' =>
               state <= NSCar;
            WHEN others => 
         END CASE;
      END IF; 
   END PROCESS;
END pure_logic;

cmsc132/vhdl/trafficlite/trafficlite_tb.vhdl
LIBRARY ieee;
USE ieee.std_logic_1164.all;
ENTITY trafficlite_tb IS
END trafficlite_tb;
ARCHITECTURE behavior OF trafficlite_tb IS
   --100Mhz
   CONSTANT frequency: integer := 100e6; 
   CONSTANT period : time := 1000 ms / frequency;
   COMPONENT trafficlite IS
   PORT (EWCar, NSCar, clk: IN STD_LOGIC;
      EWLite, NSLite: OUT STD_LOGIC
   );
   END COMPONENT;
   SIGNAL clk : STD_LOGIC := '0';
   SIGNAL inputs : STD_LOGIC_VECTOR(1 DOWNTO 0);
   SIGNAL outputs : STD_LOGIC_VECTOR(1 DOWNTO 0);
BEGIN 
   clk <= NOT clk AFTER period / 2;
   uut: trafficlite PORT MAP (inputs(1),inputs(0),clk,outputs(1),outputs(0));
   stim_proc: PROCESS
   BEGIN
      inputs <= "00";
      WAIT FOR period / 2;
      inputs <= "10";
      WAIT FOR period / 2;
      inputs <= "01";
      WAIT FOR period / 2;
   END PROCESS;
END ARCHITECTURE;

cmsc132/vhdl/trafficlite/trafficlite_tb.vcd
$date
  Tue Sep  1 18:48:34 2020
$end
$version
  GHDL v0
$end
$timescale
  1 fs
$end
$scope module standard $end
$upscope $end
$scope module std_logic_1164 $end
$upscope $end
$scope module trafficlite_tb $end
$var reg 1 ! clk $end
$var reg 2 " inputs[1:0] $end
$var reg 2 # outputs[1:0] $end
$scope module uut $end
$var reg 1 $ ewcar $end
$var reg 1 % nscar $end
$var reg 1 & clk $end
$var reg 1 ' ewlite $end
$var reg 1 ( nslite $end
$var reg 1 ) state $end
$upscope $end
$upscope $end
$enddefinitions $end
#0
0!
b00 "
b01 #
0$
0%
0&
0'
1(
0)
#5000000
1!
1&
#10000000
0!
b10 "
1$
0&
#15000000
1!
1&
1)
#20000000
0!
b01 "
b10 #
0$
1%
0&
1'
0(
#25000000
1!
1&
#30000000
0!
b00 "
0%
0&
#35000000
1!
1&
0)
#40000000
0!
b10 "
b01 #
1$
0&
0'
1(
#45000000
1!
1&
1)
#50000000
0!
b01 "
b10 #
0$
1%
0&
1'
0(
#55000000
1!
1&
#60000000
0!
b00 "
0%
0&
#65000000
1!
1&
0)
#70000000
0!
b10 "
b01 #
1$
0&
0'
1(
#75000000
1!
1&
1)
#80000000
0!
b01 "
b10 #
0$
1%
0&
1'
0(
#85000000
1!
1&
#90000000
0!
b00 "
0%
0&
#95000000
1!
1&
0)
#100000000
0!
b10 "
b01 #
1$
0&
0'
1(
#105000000
1!
1&
1)
#110000000
0!
b01 "
b10 #
0$
1%
0&
1'
0(
#115000000
1!
1&
#120000000
0!
b00 "
0%
0&
#125000000
1!
1&
0)
#130000000
0!
b10 "
b01 #
1$
0&
0'
1(
#135000000
1!
1&
1)
#140000000
0!
b01 "
b10 #
0$
1%
0&
1'
0(
#145000000
1!
1&
#150000000
0!
b00 "
0%
0&
#155000000
1!
1&
0)
#160000000
0!
b10 "
b01 #
1$
0&
0'
1(
#165000000
1!
1&
1)
#170000000
0!
b01 "
b10 #
0$
1%
0&
1'
0(
#175000000
1!
1&
#180000000
0!
b00 "
0%
0&
#185000000
1!
1&
0)
#190000000
0!
b10 "
b01 #
1$
0&
0'
1(
#195000000
1!
1&
1)
#200000000
0!
b01 "
b10 #
0$
1%
0&
1'
0(
#205000000
1!
1&
#210000000
0!
b00 "
0%
0&
#215000000
1!
1&
0)
#220000000
0!
b10 "
b01 #
1$
0&
0'
1(
#225000000
1!
1&
1)
#230000000
0!
b01 "
b10 #
0$
1%
0&
1'
0(
#235000000
1!
1&
#240000000
0!
b00 "
0%
0&
#245000000
1!
1&
0)
#250000000
0!
b10 "
b01 #
1$
0&
0'
1(
#255000000
1!
1&
1)
#260000000
0!
b01 "
b10 #
0$
1%
0&
1'
0(
#265000000
1!
1&
#270000000
0!
b00 "
0%
0&
#275000000
1!
1&
0)
#280000000
0!
b10 "
b01 #
1$
0&
0'
1(
#285000000
1!
1&
1)
#290000000
0!
b01 "
b10 #
0$
1%
0&
1'
0(
#295000000
1!
1&
#300000000
0!
b00 "
0%
0&
#305000000
1!
1&
0)
#310000000
0!
b10 "
b01 #
1$
0&
0'
1(
#315000000
1!
1&
1)
#320000000
0!
b01 "
b10 #
0$
1%
0&
1'
0(
#325000000
1!
1&
#330000000
0!
b00 "
0%
0&
#335000000
1!
1&
0)
#340000000
0!
b10 "
b01 #
1$
0&
0'
1(
#345000000
1!
1&
1)
#350000000
0!
b01 "
b10 #
0$
1%
0&
1'
0(
#355000000
1!
1&
#360000000
0!
b00 "
0%
0&
#365000000
1!
1&
0)
#370000000
0!
b10 "
b01 #
1$
0&
0'
1(
#375000000
1!
1&
1)
#380000000
0!
b01 "
b10 #
0$
1%
0&
1'
0(
#385000000
1!
1&
#390000000
0!
b00 "
0%
0&
#395000000
1!
1&
0)
#400000000
0!
b10 "
b01 #
1$
0&
0'
1(
#405000000
1!
1&
1)
#410000000
0!
b01 "
b10 #
0$
1%
0&
1'
0(
#415000000
1!
1&
#420000000
0!
b00 "
0%
0&
#425000000
1!
1&
0)
#430000000
0!
b10 "
b01 #
1$
0&
0'
1(
#435000000
1!
1&
1)
#440000000
0!
b01 "
b10 #
0$
1%
0&
1'
0(
#445000000
1!
1&
#450000000
0!
b00 "
0%
0&
#455000000
1!
1&
0)
#460000000
0!
b10 "
b01 #
1$
0&
0'
1(
#465000000
1!
1&
1)
#470000000
0!
b01 "
b10 #
0$
1%
0&
1'
0(
#475000000
1!
1&
#480000000
0!
b00 "
0%
0&
#485000000
1!
1&
0)
#490000000
0!
b10 "
b01 #
1$
0&
0'
1(
#495000000
1!
1&
1)
#500000000
0!
b01 "
b10 #
0$
1%
0&
1'
0(
