cmsc132/vhdl/38decoder/decoder_3to8.vhdl
LIBRARY ieee;
USE ieee.std_logic_1164.all;
---------------------------------
ENTITY decoder_3to8 IS
   PORT (
      INPUT: IN STD_LOGIC_VECTOR(2 downto 0);
      OUTPUT: OUT STD_LOGIC_VECTOR(7 downto 0)
   );
END decoder_3to8;
--------------------------------

ARCHITECTURE pure_logic OF decoder_3to8 IS
BEGIN
   OUTPUT(0) <= NOT INPUT(2) AND NOT INPUT(1) and NOT INPUT(0);
   OUTPUT(1) <= NOT INPUT(2) AND NOT INPUT(1) and INPUT(0);
   OUTPUT(2) <= NOT INPUT(2) AND INPUT(1) and NOT INPUT(0);
   OUTPUT(3) <= NOT INPUT(2) AND INPUT(1) and INPUT(0);
   OUTPUT(4) <= INPUT(2) AND NOT INPUT(1) and NOT INPUT(0);
   OUTPUT(5) <= INPUT(2) AND NOT INPUT(1) and INPUT(0);
   OUTPUT(6) <= INPUT(2) AND INPUT(1) and NOT INPUT(0);
   OUTPUT(7) <= INPUT(2) AND INPUT(1) and INPUT(0);
END pure_logic;

cmsc132/vhdl/38decoder/decoder_3to8_tb.vhdl
LIBRARY ieee;
USE ieee.std_logic_1164.all;

ENTITY decoder_3to8_tb IS
END decoder_3to8_tb;

architecture behavior of decoder_3to8_tb is
   component decoder_3to8 is 
      port (
         INPUT: IN STD_LOGIC_VECTOR(2 downto 0);
         OUTPUT: OUT STD_LOGIC_VECTOR(7 downto 0));
   end component;
   signal INPUT_TB: STD_LOGIC_VECTOR(2 downto 0);
   signal OUTPUT_TB: STD_LOGIC_VECTOR(7 downto 0);

begin 
   uut: decoder_3to8 port map (
      INPUT => INPUT_TB,
      OUTPUT => OUTPUT_TB
   );

   stim_proc: process
   begin

      wait for 50 ns;


      INPUT_TB <= "000"; wait for 10 ns; assert OUTPUT_TB="00000001" report "000 failed,output= ";
      INPUT_TB <= "001"; wait for 10 ns; assert OUTPUT_TB="00000010" report "001 failed,output= ";
      INPUT_TB <= "010"; wait for 10 ns; assert OUTPUT_TB="00000100" report "010 failed,output= "; 
      INPUT_TB <= "011"; wait for 10 ns; assert OUTPUT_TB="00001000" report "011 failed,output= ";
      INPUT_TB <= "100"; wait for 10 ns; assert OUTPUT_TB="00010000" report "100 failed,output= ";
      INPUT_TB <= "101"; wait for 10 ns; assert OUTPUT_TB="00100000" report "101 failed,output= "; 
      INPUT_TB <= "110"; wait for 10 ns; assert OUTPUT_TB="01000000" report "110 failed,output= ";
      INPUT_TB <= "111"; wait for 10 ns; assert OUTPUT_TB="10000000" report "111 failed,output= ";
      wait;
   end process;
end;

cmsc132/vhdl/38decoder/decoder_tb.vcd
$date
  Wed Aug 19 22:37:49 2020
$end
$version
  GHDL v0
$end
$timescale
  1 fs
$end
$scope module standard $end
$upscope $end
$scope module std_logic_1164 $end
$upscope $end
$scope module decoder_3to8_tb $end
$var reg 3 ! input_tb[2:0] $end
$var reg 8 " output_tb[7:0] $end
$scope module uut $end
$var reg 3 # input[2:0] $end
$var reg 8 $ output[7:0] $end
$upscope $end
$upscope $end
$enddefinitions $end
#0
bUUU !
bUUUUUUUU "
bUUU #
bUUUUUUUU $
#50000000
b000 !
b00000001 "
b000 #
b00000001 $
#60000000
b001 !
b00000010 "
b001 #
b00000010 $
#70000000
b010 !
b00000100 "
b010 #
b00000100 $
#80000000
b011 !
b00001000 "
b011 #
b00001000 $
#90000000
b100 !
b00010000 "
b100 #
b00010000 $
#100000000
b101 !
b00100000 "
b101 #
b00100000 $
#110000000
b110 !
b01000000 "
b110 #
b01000000 $
#120000000
b111 !
b10000000 "
b111 #
b10000000 $
