cmsc132/vhdl/ALU_1bit/mux_2to1.vhdl
LIBRARY ieee;
USE ieee.std_logic_1164.all;
---------------------------------
ENTITY mux_2to1 IS
   PORT (A, B, S: IN STD_LOGIC;
   C: OUT STD_LOGIC);
END mux_2to1;
--------------------------------

ARCHITECTURE pure_logic OF mux_2to1 IS
BEGIN
--- C <= (A AND NOT S) OR (B AND S);                       
   C <= A WHEN S='0' ELSE B;
END pure_logic;

cmsc132/vhdl/and_or/or.vhdl
LIBRARY ieee;
USE ieee.std_logic_1164.all;
---------------------------------
ENTITY or_gate IS
   PORT (A, B: IN STD_LOGIC;
   C: OUT STD_LOGIC);
END or_gate;
--------------------------------

ARCHITECTURE pure_logic OF or_gate IS
BEGIN
   C <= A  OR B;
END pure_logic;

cmsc132/vhdl/reg_file/and.vhdl
LIBRARY ieee;
USE ieee.std_logic_1164.all;
---------------------------------
ENTITY and_gate IS
   PORT (A, B: IN STD_LOGIC;
   C: OUT STD_LOGIC);
END and_gate;
--------------------------------

ARCHITECTURE pure_logic OF and_gate IS
BEGIN
   C <= A  AND B;
END pure_logic;

cmsc132/vhdl/and_or/and_or.vhdl
LIBRARY ieee;
USE ieee.std_logic_1164.all;
---------------------------------
ENTITY and_or IS
   PORT (a, b, op: IN STD_LOGIC;
   result: OUT STD_LOGIC);
END and_or;
--------------------------------

ARCHITECTURE behavioral OF and_or IS

   COMPONENT mux_2to1 IS
      PORT (A, B, S: IN STD_LOGIC;
      C: OUT STD_LOGIC);
   END COMPONENT;

   COMPONENT and_gate IS
      PORT (A, B: IN STD_LOGIC;
      C: OUT STD_LOGIC);
   END COMPONENT;

   COMPONENT or_gate IS
      PORT (A, B: IN STD_LOGIC;
      C: OUT STD_LOGIC);
   END COMPONENT;

   signal u: STD_LOGIC;
   signal v: STD_LOGIC;

BEGIN

   u1: and_gate port map(a, b, u);
   u2: or_gate port map(a, b, v);
   u3: mux_2to1 port map(u, v, op, result); 

END behavioral;

cmsc132/vhdl/and_or/and_or_tb.vhdl
LIBRARY ieee;
USE ieee.std_logic_1164.all;

ENTITY and_or_tb IS
END and_or_tb;

architecture behavior of and_or_tb is
   component and_or is 
      port (
         a, b, op: IN STD_LOGIC;
         result: OUT STD_LOGIC);
   end component;

   signal input: STD_LOGIC_VECTOR(2 downto 0);
   signal output: STD_LOGIC;

begin 
   uut: and_or port map (
      a => input(0),
      b => input(1),
      op => input(0),
      result => output
   );

   stim_proc: process
   begin
      input <= "000"; wait for 10 ns; assert output='0' report "000 failed,output= " & std_logic'image(output);
      input <= "001"; wait for 10 ns; assert output='0' report "001 failed,output= " & std_logic'image(output);
      input <= "010"; wait for 10 ns; assert output='0' report "011 failed,output= " & std_logic'image(output);
      input <= "011"; wait for 10 ns; assert output='1' report "011 failed,output= " & std_logic'image(output);
      input <= "100"; wait for 10 ns; assert output='0' report "100 failed,output= " & std_logic'image(output);
      input <= "101"; wait for 10 ns; assert output='1' report "100 failed,output= " & std_logic'image(output);
      input <= "110"; wait for 10 ns; assert output='1' report "110 failed,output= " & std_logic'image(output);
      input <= "111"; wait for 10 ns; assert output='1' report "111 failed,output= " & std_logic'image(output);
      wait;
   end process;
end;

cmsc132/vhdl/and_or/and_or_tb.vcd
$date
  Thu Aug 20 15:44:01 2020
$end
$version
  GHDL v0
$end
$timescale
  1 fs
$end
$scope module standard $end
$upscope $end
$scope module std_logic_1164 $end
$upscope $end
$scope module and_or_tb $end
$var reg 3 ! input[2:0] $end
$var reg 1 " output $end
$scope module uut $end
$var reg 1 # a $end
$var reg 1 $ b $end
$var reg 1 % op $end
$var reg 1 & result $end
$var reg 1 ' u $end
$var reg 1 ( v $end
$scope module u1 $end
$var reg 1 ) a $end
$var reg 1 * b $end
$var reg 1 + c $end
$upscope $end
$scope module u2 $end
$var reg 1 , a $end
$var reg 1 - b $end
$var reg 1 . c $end
$upscope $end
$scope module u3 $end
$var reg 1 / a $end
$var reg 1 0 b $end
$var reg 1 1 s $end
$var reg 1 2 c $end
$upscope $end
$upscope $end
$upscope $end
$enddefinitions $end
#0
b000 !
0"
0#
0$
0%
0&
0'
0(
0)
0*
0+
0,
0-
0.
0/
00
01
02
#10000000
b001 !
1"
1#
1%
1&
1(
1)
1,
1.
10
11
12
#20000000
b010 !
0"
0#
1$
0%
0&
0)
1*
0,
1-
01
02
#30000000
b011 !
1"
1#
1%
1&
1'
1)
1+
1,
1/
11
12
#40000000
b100 !
0"
0#
0$
0%
0&
0'
0(
0)
0*
0+
0,
0-
0.
0/
00
01
02
#50000000
b101 !
1"
1#
1%
1&
1(
1)
1,
1.
10
11
12
#60000000
b110 !
0"
0#
1$
0%
0&
0)
1*
0,
1-
01
02
#70000000
b111 !
1"
1#
1%
1&
1'
1)
1+
1,
1/
11
12
