cmsc132/vhdl/ALU_1bit/mux_2to1.vhdl
LIBRARY ieee;
USE ieee.std_logic_1164.all;
---------------------------------
ENTITY mux_2to1 IS
   PORT (A, B, S: IN STD_LOGIC;
   C: OUT STD_LOGIC);
END mux_2to1;
--------------------------------

ARCHITECTURE pure_logic OF mux_2to1 IS
BEGIN
--- C <= (A AND NOT S) OR (B AND S);                       
   C <= A WHEN S='0' ELSE B;
END pure_logic;

cmsc132/vhdl/and_or/or.vhdl
LIBRARY ieee;
USE ieee.std_logic_1164.all;
---------------------------------
ENTITY or_gate IS
   PORT (A, B: IN STD_LOGIC;
   C: OUT STD_LOGIC);
END or_gate;
--------------------------------

ARCHITECTURE pure_logic OF or_gate IS
BEGIN
   C <= A  OR B;
END pure_logic;

cmsc132/vhdl/reg_file/and.vhdl
LIBRARY ieee;
USE ieee.std_logic_1164.all;
---------------------------------
ENTITY and_gate IS
   PORT (A, B: IN STD_LOGIC;
   C: OUT STD_LOGIC);
END and_gate;
--------------------------------

ARCHITECTURE pure_logic OF and_gate IS
BEGIN
   C <= A  AND B;
END pure_logic;

cmsc132/vhdl/and_or/and_or.vhdl
LIBRARY ieee;
USE ieee.std_logic_1164.all;
---------------------------------
ENTITY and_or IS
   PORT (a, b, Operation: IN STD_LOGIC;
   Result: OUT STD_LOGIC);
END and_or;
--------------------------------
ARCHITECTURE behavioral OF and_or IS
   COMPONENT mux_2to1 IS
      PORT (A, B, S: IN STD_LOGIC;
      C: OUT STD_LOGIC);
   END COMPONENT;
   COMPONENT and_gate IS
      PORT (A, B: IN STD_LOGIC;
      C: OUT STD_LOGIC);
   END COMPONENT;
   COMPONENT or_gate IS
      PORT (A, B: IN STD_LOGIC;
      C: OUT STD_LOGIC);
   END COMPONENT;
   SIGNAL u: STD_LOGIC;
   SIGNAL v: STD_LOGIC;
BEGIN
   u1_and: and_gate port map(a, b, u);
   u2_or: or_gate port map(a, b, v);
   u3_mux: mux_2to1 port map(u, v,
                   Operation,
                   Result); 
END behavioral;

cmsc132/vhdl/and_or/and_or_tb.vhdl
LIBRARY ieee;
USE ieee.std_logic_1164.all;
ENTITY and_or_tb IS
END and_or_tb;
ARCHITECTURE behavior OF and_or_tb IS
   COMPONENT and_or IS 
      PORT (
         a, b, Operation: IN STD_LOGIC;
         Result: OUT STD_LOGIC);
   END COMPONENT;
   SIGNAL input: STD_LOGIC_VECTOR(2 DOWNTO 0);
   SIGNAL output: STD_LOGIC;
BEGIN 
   UUT: and_or PORT MAP (
      Operation => input(2),
      a => input(1),
      b => input(0),
      Result => output
   );
   STIM_PROC: PROCESS
   BEGIN
      input <= "000"; WAIT FOR 10 NS; ASSERT output='0' REPORT "000 failed,output= " & STD_LOGIC'IMAGE(output);
      input <= "001"; WAIT FOR 10 NS; ASSERT output='0' REPORT "001 failed,output= " & STD_LOGIC'IMAGE(output);
      input <= "010"; WAIT FOR 10 NS; ASSERT output='0' REPORT "010 failed,output= " & STD_LOGIC'IMAGE(output);
      input <= "011"; WAIT FOR 10 NS; ASSERT output='1' REPORT "011 failed,output= " & STD_LOGIC'IMAGE(output);
      input <= "100"; WAIT FOR 10 NS; ASSERT output='0' REPORT "100 failed,output= " & STD_LOGIC'IMAGE(output);
      input <= "101"; WAIT FOR 10 NS; ASSERT output='1' REPORT "101 failed,output= " & STD_LOGIC'IMAGE(output);
      input <= "110"; WAIT FOR 10 NS; ASSERT output='1' REPORT "110 failed,output= " & STD_LOGIC'IMAGE(output);
      input <= "111"; WAIT FOR 10 NS; ASSERT output='1' REPORT "111 failed,output= " & STD_LOGIC'IMAGE(output);
      WAIT;
   END PROCESS;
END;

cmsc132/vhdl/and_or/and_or_tb.vcd
$date
  Wed Sep 14 22:17:35 2022
$end
$version
  GHDL v0
$end
$timescale
  1 fs
$end
$scope module standard $end
$upscope $end
$scope module std_logic_1164 $end
$upscope $end
$scope module and_or_tb $end
$var reg 3 ! input[2:0] $end
$var reg 1 " output $end
$scope module uut $end
$var reg 1 # a $end
$var reg 1 $ b $end
$var reg 1 % operation $end
$var reg 1 & result $end
$var reg 1 ' u $end
$var reg 1 ( v $end
$scope module u1_and $end
$var reg 1 ) a $end
$var reg 1 * b $end
$var reg 1 + c $end
$upscope $end
$scope module u2_or $end
$var reg 1 , a $end
$var reg 1 - b $end
$var reg 1 . c $end
$upscope $end
$scope module u3_mux $end
$var reg 1 / a $end
$var reg 1 0 b $end
$var reg 1 1 s $end
$var reg 1 2 c $end
$upscope $end
$upscope $end
$upscope $end
$enddefinitions $end
#0
b000 !
0"
0#
0$
0%
0&
0'
0(
0)
0*
0+
0,
0-
0.
0/
00
01
02
#10000000
b001 !
1$
1(
1*
1-
1.
10
#20000000
b010 !
1#
0$
1)
0*
1,
0-
#30000000
b011 !
1"
1$
1&
1'
1*
1+
1-
1/
12
#40000000
b100 !
0"
0#
0$
1%
0&
0'
0(
0)
0*
0+
0,
0-
0.
0/
00
11
02
#50000000
b101 !
1"
1$
1&
1(
1*
1-
1.
10
12
#60000000
b110 !
1#
0$
1)
0*
1,
0-
#70000000
b111 !
1$
1'
1*
1+
1-
1/
